pyconizer/__init__.py
pyconizer/lib/__init__.py
pyconizer/lib/url.py
pyconizer/lib/api/__init__.py
pyconizer/lib/api/structure.py
pyconizer/lib/api/image/__init__.py
pyconizer/lib/api/sld/__init__.py
pyconizer/lib/api/sld/v1_0_0/__init__.py
pyconizer/lib/api/sld/v1_0_0/classes.py
pyconizer/lib/api/sld/v1_0_0/schema.xsd
pyconizer/lib/api/sld/v1_0_0/sub_classes.py
pyconizer/lib/api/svg/__init__.py
pyconizer/lib/api/svg/templates/circle.xml
pyconizer/lib/api/svg/templates/line.xml
pyconizer/lib/api/svg/templates/polygon.xml
pyconizer/lib/api/svg/templates/svg_1_0.xml
pyconizer-0.1.4.dist-info/DESCRIPTION.rst
pyconizer-0.1.4.dist-info/METADATA
pyconizer-0.1.4.dist-info/RECORD
pyconizer-0.1.4.dist-info/WHEEL
pyconizer-0.1.4.dist-info/entry_points.txt
pyconizer-0.1.4.dist-info/metadata.json
pyconizer-0.1.4.dist-info/top_level.txt
